MANIFEST.in
README.rst
gdshortener.py
setup.cfg
setup.py
gdshortener.egg-info/PKG-INFO
gdshortener.egg-info/SOURCES.txt
gdshortener.egg-info/dependency_links.txt
gdshortener.egg-info/requires.txt
gdshortener.egg-info/top_level.txt