Metadata-Version: 1.1
Name: gdshortener
Version: 1.0.1
Summary: A module that provides access to .gd URL Shortener
Home-page: https://github.com/torre76/gd_shortener
Author: Gian Luca Dalla Torre
Author-email: gianluca@gestionaleauto.com
License: LGPL
Download-URL: https://github.com/torre76/gd_shortener/tarball/1.0.1
Keywords: url shortener gd
Platform: UNKNOWN
Classifier: Development Status :: 5 - Production/Stable
Classifier: Topic :: Software Development :: Libraries :: Python Modules
Classifier: License :: OSI Approved :: GNU Library or Lesser General Public License (LGPL)
Classifier: Programming Language :: Python :: 2.6
Classifier: Programming Language :: Python :: 2.7
Classifier: Programming Language :: Python :: 3
